LICENSE.txt
MANIFEST.in
README.rst
setup.py
jk_fileaccess/AbstractFileInterface.py
jk_fileaccess/AbstractFilePathFilter.py
jk_fileaccess/AbstractShare.py
jk_fileaccess/CifsShare.py
jk_fileaccess/LocalFileInterface.py
jk_fileaccess/LocalShare.py
jk_fileaccess/PrefixFilePathFilter.py
jk_fileaccess/SftpShare.py
jk_fileaccess/ShareFactory.py
jk_fileaccess/SshRemoteFileInterface.py
jk_fileaccess/__init__.py
jk_fileaccess.egg-info/PKG-INFO
jk_fileaccess.egg-info/SOURCES.txt
jk_fileaccess.egg-info/dependency_links.txt
jk_fileaccess.egg-info/not-zip-safe
jk_fileaccess.egg-info/requires.txt
jk_fileaccess.egg-info/top_level.txt