Metadata-Version: 1.1
Name: jk-fileaccess
Version: 0.2017.10.7
Summary: Provides a uniform interface to process files that are either stored locally or remotely.
Home-page: https://github.com/jkpubsrc/python-module-jk-fileaccess
Author: Jürgen Knauth
Author-email: pubsrc@binary-overflow.de
License: Apache 2.0
Download-URL: https://github.com/jkpubsrc/python-module-jk-fileaccess/tarball/0.2017.10.7
Keywords: file,filesystem,ssh,sftp,cifs,smb,iterating
Platform: UNKNOWN
Classifier: Development Status :: 4 - Beta
Classifier: Programming Language :: Python :: 3.5
Classifier: License :: OSI Approved :: Apache Software License
